pnet/api.py
pnet/__init__.py
pnet/TEMPLATE_configuration.py
phishnet_api-1.0.2.dist-info/DESCRIPTION.rst
phishnet_api-1.0.2.dist-info/metadata.json
phishnet_api-1.0.2.dist-info/METADATA
phishnet_api-1.0.2.dist-info/WHEEL
phishnet_api-1.0.2.dist-info/RECORD
phishnet_api-1.0.2.dist-info/top_level.txt
phishnet_api-1.0.2.dist-info/pbr.json
