Metadata-Version: 2.0
Name: phishnet-api
Version: 1.0.2
Summary: A wrapper for the phish.net API
Home-page: https://github.com/iloveagent57/phishnet-api
Author: Alex Dusenbery
Author-email: UNKNOWN
License: MIT
Keywords: api wrapper phish
Platform: UNKNOWN
Requires-Dist: requests (==2.0.1)
Requires-Dist: mock (==1.3.0)
